MANIFEST.in
README.md
requirements.txt
requirements_dev.txt
setup.py
aws_lambda_fsm/__init__.py
aws_lambda_fsm/_pkg_meta.py
aws_lambda_fsm/action.py
aws_lambda_fsm/aws.py
aws_lambda_fsm/client.py
aws_lambda_fsm/config.py
aws_lambda_fsm/constants.py
aws_lambda_fsm/fsm.py
aws_lambda_fsm/handler.py
aws_lambda_fsm/serialization.py
aws_lambda_fsm/state.py
aws_lambda_fsm/transition.py
aws_lambda_fsm/utils.py
aws_lambda_fsm.egg-info/PKG-INFO
aws_lambda_fsm.egg-info/SOURCES.txt
aws_lambda_fsm.egg-info/dependency_links.txt
aws_lambda_fsm.egg-info/requires.txt
aws_lambda_fsm.egg-info/top_level.txt
tools/create_dynamodb_table.py
tools/create_kinesis_stream.py
tools/create_resources.py
tools/create_sns_topic.py
tools/create_sqs_queue.py
tools/dev_lambda.py
tools/start_state_machine.py
tools/yaml_to_graphviz.py
tools/experimental/dev_ecs.py
tools/experimental/fsm_docker_runner.py