Metadata-Version: 1.0
Name: aws-lambda-fsm
Version: 0.30.0
Summary: AWS FSMs on Lambda/Kinesis
Home-page: http://github.com/Workiva/aws-lambda-fsm-workflows
Author: Shawn Rusaw
Author-email: shawn.rusaw@workiva.com
License: http://www.apache.org/licenses/LICENSE-2.0
Platform: UNKNOWN
